okmodule.py
okmodule-1.2.0.dist-info/METADATA
okmodule-1.2.0.dist-info/WHEEL
okmodule-1.2.0.dist-info/top_level.txt
okmodule-1.2.0.dist-info/RECORD
