Metadata-Version: 2.1
Name: okmodule
Version: 1.2.0
Summary: okmodule
Home-page: https://github.com/lawley0316/okmodule
Author: Lawley
Author-email: lawley0316@gmail.com
License: MIT
Classifier: License :: OSI Approved :: MIT License
Classifier: Programming Language :: Python
Classifier: Programming Language :: Python :: 3
Classifier: Programming Language :: Python :: 3.6
Classifier: Programming Language :: Python :: Implementation :: CPython
Classifier: Programming Language :: Python :: Implementation :: PyPy
Requires-Python: >=3.6.0
